{
    "schemaVersion": 1,
    "id": "${mod_id}",
    "version": "${version}",
    "name": "${mod_name}",
    "description": "${description}",
    "authors": [
        "${mod_author}"
    ],
    "contact": {
        "homepage": "https://github.com/Raxdiam/ToastBegone",
        "sources": "https://github.com/Raxdiam/ToastBegone",
        "issues": "https://github.com/Raxdiam/ToastBegone/issues"
    },
    "license": "${license}",
    "icon": "assets/${mod_id}/icon.png",
    "environment": "*",
    "entrypoints": {
        "client": [
            "com.raxdiam.toastbegone.ToastBegoneMod"
        ],
        "modmenu": [
            "com.raxdiam.toastbegone.api.ModMenuImpl"
        ]
    },
    "mixins": [
        "${mod_id}.mixins.json",
        "${mod_id}.fabric.mixins.json"
    ],
    "depends": {
        "fabricloader": ">=${fabric_loader_version}",
        "minecraft": "${minecraft_version}",
        "java": ">=${java_version}"
    },
    "suggests": {
        "another-mod": "*"
    }
}
  